lance_namespace_impls/__init__.py
lance_namespace_impls/glue.py
lance_namespace_impls/hive2.py
lance_namespace_impls/hive3.py
lance_namespace_impls/iceberg.py
lance_namespace_impls/polaris.py
lance_namespace_impls/rest_client.py
lance_namespace_impls/schema.py
lance_namespace_impls/unity.py
lance_namespace_impls-0.1.0.dist-info/METADATA
lance_namespace_impls-0.1.0.dist-info/WHEEL
lance_namespace_impls-0.1.0.dist-info/RECORD
