Metadata-Version: 2.4
Name: lance-namespace-impls
Version: 0.1.0
Summary: Third-party catalog implementations for Lance Namespace
License: Apache-2.0
Requires-Python: >=3.10
Requires-Dist: lance-namespace-urllib3-client>=0.4.2
Requires-Dist: pyarrow>=15.0.0
Requires-Dist: pylance>=0.26.0
Requires-Dist: typing-extensions>=4.5.0
Provides-Extra: all
Requires-Dist: boto3>=1.35.0; extra == 'all'
Requires-Dist: botocore>=1.35.0; extra == 'all'
Requires-Dist: hive-metastore-client>=1.0.0; extra == 'all'
Requires-Dist: thrift>=0.13.0; extra == 'all'
Provides-Extra: dev
Requires-Dist: pytest-cov>=4.0.0; extra == 'dev'
Requires-Dist: pytest>=7.0.0; extra == 'dev'
Requires-Dist: ruff>=0.4.0; extra == 'dev'
Provides-Extra: glue
Requires-Dist: boto3>=1.35.0; extra == 'glue'
Requires-Dist: botocore>=1.35.0; extra == 'glue'
Provides-Extra: hive2
Requires-Dist: hive-metastore-client>=1.0.0; extra == 'hive2'
Requires-Dist: thrift>=0.13.0; extra == 'hive2'
Provides-Extra: hive3
Requires-Dist: hive-metastore-client>=1.0.0; extra == 'hive3'
Requires-Dist: thrift>=0.13.0; extra == 'hive3'
Provides-Extra: iceberg
Provides-Extra: polaris
Provides-Extra: unity
